textual_code/__init__.py
textual_code/app.py
textual_code/modals.py
textual_code/style.tcss
textual_code/utils.py
textual_code-0.0.2.dist-info/METADATA
textual_code-0.0.2.dist-info/WHEEL
textual_code-0.0.2.dist-info/entry_points.txt
textual_code-0.0.2.dist-info/RECORD
