Metadata-Version: 2.4
Name: textual-code
Version: 0.0.2
Summary: Code editor for who don't know how to use vi
Project-URL: Repository, https://github.com/rishubil/textual-code.git
Project-URL: Changelog, https://github.com/rishubil/textual-code/blob/master/CHANGELOG.md
Author-email: Nesswit <rishubil@gmail.com>
Classifier: Development Status :: 3 - Alpha
Classifier: Environment :: Console
Classifier: Intended Audience :: Developers
Classifier: License :: OSI Approved :: MIT License
Classifier: Operating System :: MacOS
Classifier: Operating System :: Microsoft :: Windows :: Windows 10
Classifier: Operating System :: Microsoft :: Windows :: Windows 11
Classifier: Operating System :: POSIX :: Linux
Classifier: Programming Language :: Python :: 3.12
Classifier: Topic :: Text Editors
Requires-Python: >=3.12
Requires-Dist: textual[syntax]>=1.0.0
